AUTHORS
CHANGELOG.txt
LICENSE
MANIFEST.in
setup.py
django_mailwhimp.egg-info/PKG-INFO
django_mailwhimp.egg-info/SOURCES.txt
django_mailwhimp.egg-info/dependency_links.txt
django_mailwhimp.egg-info/not-zip-safe
django_mailwhimp.egg-info/requires.txt
django_mailwhimp.egg-info/top_level.txt
mailwhimp/__init__.py
mailwhimp/admin.py
mailwhimp/models.py
mailwhimp/migrations/0001_initial.py
mailwhimp/migrations/0002_auto__del_field_list_default_from_subject__add_field_list_default_subj.py
mailwhimp/migrations/0003_auto__del_field_campaign_application__add_field_campaign_list.py
mailwhimp/migrations/__init__.py