Metadata-Version: 1.0
Name: django-mailwhimp
Version: 0.1
Summary: django-mailwhimp integrates mailchimp into Django
Home-page: http://github.com/Celc/django-mailwhimp
Author: Kit Sunde
Author-email: kit@mediapop.co
License: UNKNOWN
Platform: UNKNOWN
Classifier: Intended Audience :: Developers
Classifier: Intended Audience :: System Administrators
Classifier: Operating System :: OS Independent
Classifier: Programming Language :: Python
Classifier: License :: OSI Approved :: MIT License
Classifier: Topic :: Software Development :: Libraries :: Python Modules
Classifier: Framework :: Django
